[
  {
    "line": 1,
    "elements": [
      {
        "line": 10,
        "name": "User is redirected to federated provider",
        "description": "",
        "id": "verify-orderid;user-is-redirected-to-federated-provider;;2",
        "type": "scenario",
        "keyword": "Scenario Outline",
        "steps": [
          {
            "result": {
              "status": "undefined"
            },
            "line": 5,
            "name": "User enters end points",
            "match": {},
            "keyword": "Given "
          },
          {
            "result": {
              "status": "undefined"
            },
            "line": 6,
            "name": "User enters the Order ID \"data\" and rownumber 0",
            "match": {},
            "matchedColumns": [
              0,
              1
            ],
            "keyword": "Then "
          }
        ],
        "tags": [
          {
            "line": 3,
            "name": "@OrderId"
          }
        ]
      },
      {
        "line": 11,
        "name": "User is redirected to federated provider",
        "description": "",
        "id": "verify-orderid;user-is-redirected-to-federated-provider;;3",
        "type": "scenario",
        "keyword": "Scenario Outline",
        "steps": [
          {
            "result": {
              "status": "undefined"
            },
            "line": 5,
            "name": "User enters end points",
            "match": {},
            "keyword": "Given "
          },
          {
            "result": {
              "status": "undefined"
            },
            "line": 6,
            "name": "User enters the Order ID \"data\" and rownumber 1",
            "match": {},
            "matchedColumns": [
              0,
              1
            ],
            "keyword": "Then "
          }
        ],
        "tags": [
          {
            "line": 3,
            "name": "@OrderId"
          }
        ]
      }
    ],
    "name": "Verify OrderId",
    "description": "",
    "id": "verify-orderid",
    "keyword": "Feature",
    "uri": "verifyorder.feature"
  }
]